{
    "title": "Black Orpheus",
    "description": "Provided to YouTube by The Orchard Enterprises\n\nBlack Orpheus \u00b7 Ginger Tunes\n\nJazz Lounge Essentials\n\n\u2117 2015 Deep Sleep Music\n\nReleased on: 2015-01-28\n\nAuto-generated by YouTube.",
    "referenceId": "nlc5bLcKSLg",
    "date_created": "1482281666",
    "date_modified": "1482281666",
    "tags": null,
    "sourceId": "4",
    "VIDEO_LENGTH": "LONG",
    "status": "approved",
    "visibility": "1",
    "category_id_1": null,
    "category_id_2": null,
    "product_category": null,
    "video_type": null,
    "VV_VI": "154",
    "CVV_VI": null,
    "engagement_score": "2",
    "conversion_score": null,
    "id": "83106078",
    "loginId": "1758799",
    "entityType": "1",
    "titleTextEncoded": "Black-Orpheus",
    "category": null,
    "duration": 250,
    "settings": null,
    "asset": {
        "type": "youtube",
        "author": "Ginger Tunes - Topic",
        "hdvFlag": 1,
        "description": "Provided to YouTube by The Orchard Enterprises\n\nBlack Orpheus \u00b7 Ginger Tunes\n\nJazz Lounge Essentials\n\n\u2117 2015 Deep Sleep Music\n\nReleased on: 2015-01-28\n\nAuto-generated by YouTube.",
        "tags": "",
        "thumbnailUrl": "https:\/\/i.ytimg.com\/vi\/nlc5bLcKSLg\/hqdefault.jpg",
        "videoId": "nlc5bLcKSLg",
        "mediaDuration": 250,
        "prettyDuration": "00:04:10"
    },
    "transcripts": null,
    "metrics_statistics": "{\"VV_VI\":{\"engagement_score\":{\"lastUpdatedDate\":\"2017-11-17\"}}}",
    "tvp_profiles": [
        "25",
        "9",
        "18"
    ],
    "tvp_profiles_manual": null,
    "tvp_profiles_maxscore": 228.10013
}